LICENSE.txt
MANIFEST.in
README.rst
TODO.rst
pavement.py
requirements.txt
setup.cfg
setup.py
docs/conf.py
docs/index.rst
docs/readme.rst
docs/todo.rst
docs/usage.rst
sphinxcontrib/__init__.py
sphinxcontrib/programscreenshot.py
sphinxcontrib_programscreenshot.egg-info/PKG-INFO
sphinxcontrib_programscreenshot.egg-info/SOURCES.txt
sphinxcontrib_programscreenshot.egg-info/dependency_links.txt
sphinxcontrib_programscreenshot.egg-info/namespace_packages.txt
sphinxcontrib_programscreenshot.egg-info/not-zip-safe
sphinxcontrib_programscreenshot.egg-info/requires.txt
sphinxcontrib_programscreenshot.egg-info/top_level.txt