Metadata-Version: 1.1
Name: sphinxcontrib-programscreenshot
Version: 0.0.5
Summary: Sphinx extension to include screenshot of programs
Home-page: https://github.com/ponty/sphinxcontrib-programscreenshot
Author: ponty
Author-email: UNKNOWN
License: BSD
Keywords: sphinx screenshot
Platform: UNKNOWN
Classifier: License :: OSI Approved :: BSD License
Classifier: Natural Language :: English
Classifier: Operating System :: POSIX :: Linux
Classifier: Programming Language :: Python
Classifier: Environment :: Console
Classifier: Environment :: Web Environment
Classifier: Intended Audience :: Developers
Classifier: Topic :: Documentation
Classifier: Topic :: Utilities
